django_flow_forge/__init__.py
django_flow_forge/admin.py
django_flow_forge/apps.py
django_flow_forge/async_utils.py
django_flow_forge/authorization.py
django_flow_forge/auto_register_pipelines.py
django_flow_forge/batch_utils.py
django_flow_forge/models.py
django_flow_forge/pipeline_engine.py
django_flow_forge/task_utils.py
django_flow_forge/tests.py
django_flow_forge/urls.py
django_flow_forge/views.py
django_flow_forge/migrations/0001_initial.py
django_flow_forge/migrations/0002_alter_executedflow_status_alter_executedtask_status.py
django_flow_forge/migrations/0003_alter_executedtask_exceptions.py
django_flow_forge/migrations/0004_alter_executedflow_exceptions_and_more.py
django_flow_forge/migrations/0005_alter_flow_options.py
django_flow_forge/migrations/0006_flowtask_code_flowtask_docstring.py
django_flow_forge/migrations/0007_executedflow_params.py
django_flow_forge/migrations/0008_executedflow_meta.py
django_flow_forge/migrations/0009_flowbatch_flowbatchtempdata.py
django_flow_forge/migrations/0010_batchhandler.py
django_flow_forge/migrations/0011_remove_flowbatchtempdata_batch_and_more.py
django_flow_forge/migrations/0012_rename_total_batches_batchhandler_total_batch_count.py
django_flow_forge/migrations/0013_remove_batchtempdata_batch_handler_flowbatch_and_more.py
django_flow_forge/migrations/0014_delete_batchtempdata.py
django_flow_forge/migrations/0015_batchhandler_date_initialised.py
django_flow_forge/migrations/0016_executedflow_flow_batch.py
django_flow_forge/migrations/0017_alter_executedflow_options.py
django_flow_forge/migrations/0018_mlmodel.py
django_flow_forge/migrations/0019_remove_mlresult_metrics_mlresult_evaluation_metrics_and_more.py
django_flow_forge/migrations/0020_remove_mlresult_feature_importances.py
django_flow_forge/migrations/0021_remove_mlresult_notes_mlresult_metadata.py
django_flow_forge/migrations/0022_rename_executedflow_executedpipeline_and_more.py
django_flow_forge/migrations/0023_alter_pipeline_options_and_more.py
django_flow_forge-0.9.9.dist-info/LICENSE
django_flow_forge-0.9.9.dist-info/WHEEL
django_flow_forge-0.9.9.dist-info/METADATA
django_flow_forge-0.9.9.dist-info/RECORD
