Metadata-Version: 2.3
Name: django-flow-forge
Version: 0.9.9
Summary: Keep Data Ops and Machine Learning Ops (MLOps) simple and vendor agnostic with this Django module for defining, running and monitoring data work flows.
Keywords: django,tasks,mlops,data,machine learning,data science,pipelines,flow,orchestration,AI,celery,htmx
Author-email: Ed Burmicz <eddyojb@gmail.com>
Requires-Python: >=3.9
Classifier: Framework :: Django
Classifier: Programming Language :: Python :: 3
Classifier: License :: OSI Approved :: MIT License
Classifier: Operating System :: OS Independent
Requires-Dist: Django>=5
Requires-Dist: django-htmx
Project-URL: Homepage, https://github.com/eddyojb88/django-flow-forge
